napari_utrack_loader/__init__.py
napari_utrack_loader/_widget.py
napari_utrack_loader/napari.yaml
napari_utrack_loader/_tests/__init__.py
napari_utrack_loader-0.0.1.dist-info/LICENSE
napari_utrack_loader-0.0.1.dist-info/METADATA
napari_utrack_loader-0.0.1.dist-info/WHEEL
napari_utrack_loader-0.0.1.dist-info/entry_points.txt
napari_utrack_loader-0.0.1.dist-info/top_level.txt
napari_utrack_loader-0.0.1.dist-info/RECORD
