Metadata-Version: 2.1
Name: napari-utrack-loader
Version: 0.0.1
Summary: A simple plugin to load images, detections and tracks from the u-track software into napari
Author: Jules Vanaret
Author-email: jules.vanaret@univ-amu.fr
License: 
Project-URL: Bug Tracker, https://github.com/jules-vanaret/napari-utrack-loader/issues
Project-URL: Documentation, https://github.com/jules-vanaret/napari-utrack-loader#README.md
Project-URL: Source Code, https://github.com/jules-vanaret/napari-utrack-loader
Project-URL: User Support, https://github.com/jules-vanaret/napari-utrack-loader/issues
Classifier: Development Status :: 2 - Pre-Alpha
Classifier: Framework :: napari
Classifier: Intended Audience :: Developers
Classifier: License :: OSI Approved :: MIT License
Classifier: Operating System :: OS Independent
Classifier: Programming Language :: Python
Classifier: Programming Language :: Python :: 3
Classifier: Programming Language :: Python :: 3 :: Only
Classifier: Programming Language :: Python :: 3.9
Classifier: Programming Language :: Python :: 3.10
Classifier: Programming Language :: Python :: 3.11
Classifier: Programming Language :: Python :: 3.12
Classifier: Topic :: Scientific/Engineering :: Image Processing
Requires-Python: >=3.9
License-File: LICENSE
Requires-Dist: numpy
Requires-Dist: magicgui
Requires-Dist: qtpy
Requires-Dist: tifffile
Provides-Extra: testing
Requires-Dist: tox ; extra == 'testing'
Requires-Dist: pytest ; extra == 'testing'
Requires-Dist: pytest-cov ; extra == 'testing'
Requires-Dist: pytest-qt ; extra == 'testing'
Requires-Dist: napari ; extra == 'testing'
Requires-Dist: pyqt5 ; extra == 'testing'
